mailerlite/__init__.py
mailerlite/_version.py
mailerlite/account.py
mailerlite/api.py
mailerlite/campaign.py
mailerlite/client.py
mailerlite/constants.py
mailerlite/field.py
mailerlite/group.py
mailerlite/segment.py
mailerlite/subscriber.py
mailerlite/testing.py
mailerlite/webhook.py
mailerlite/tests/__init__.py
mailerlite/tests/conftest.py
mailerlite/tests/test_account.py
mailerlite/tests/test_api.py
mailerlite/tests/test_campaign.py
mailerlite/tests/test_client.py
mailerlite/tests/test_field.py
mailerlite/tests/test_group.py
mailerlite/tests/test_segment.py
mailerlite/tests/test_subscriber.py
mailerlite/tests/test_webhook.py
mailerlite_api_python-0.10.0.dist-info/AUTHORS.rst
mailerlite_api_python-0.10.0.dist-info/LICENSE
mailerlite_api_python-0.10.0.dist-info/METADATA
mailerlite_api_python-0.10.0.dist-info/WHEEL
mailerlite_api_python-0.10.0.dist-info/entry_points.txt
mailerlite_api_python-0.10.0.dist-info/top_level.txt
mailerlite_api_python-0.10.0.dist-info/RECORD
