Metadata-Version: 2.1
Name: mailerlite-api-python
Version: 0.10.0
Summary: Python Wrapper for Mailerlite API
Home-page: https://github.com/skoudoro/mailerlite-api-python
Author: skoudoro
Author-email: skab12@gmail.com
License: BSD (3-clause)
Keywords: mailerlite-SDK mailerlite python wrapper
Platform: UNKNOWN
Classifier: Development Status :: 4 - Beta
Classifier: Natural Language :: English
Classifier: Programming Language :: Python :: 3
Requires-Python: >=3.6
License-File: LICENSE
License-File: AUTHORS.rst
